json_extractor/__init__.py
json_extractor/extractor.py
tests/__init__.py
tests/test_extractor.py
JsonExtractor-0.0.2.dist-info/LICENSE
JsonExtractor-0.0.2.dist-info/METADATA
JsonExtractor-0.0.2.dist-info/WHEEL
JsonExtractor-0.0.2.dist-info/top_level.txt
JsonExtractor-0.0.2.dist-info/RECORD
