Metadata-Version: 2.1
Name: JsonExtractor
Version: 0.0.2
Summary: A tool for extracting valid JSON from LLM responses
Home-page: https://github.com/chigwell/JsonExtractor
Author: Eugene Evstafev
Author-email: chigwel@gmail.com
Classifier: License :: OSI Approved :: MIT License
Classifier: Development Status :: 3 - Alpha
Classifier: Intended Audience :: Developers
Classifier: Programming Language :: Python :: 3
Classifier: Operating System :: OS Independent
Requires-Python: >=3.6
License-File: LICENSE
Requires-Dist: regex
